{
  "type": "forge:conditional",
  "recipes": [
    {
      "conditions": [
        {
          "type": "forge:mod_loaded",
          "modid": "powah"
        },
        {
          "type": "forge:item_exists",
          "item": "powah:dielectric_casing"
        }
      ],
      "recipe": {
        "type": "minecraft:crafting_shaped",
        "category": "misc",
        "group": "turtlechargingstation",
        "key": {
          "D": [],
          "I": {
            "tag": "forge:storage_blocks/iron"
          },
          "c": {
            "item": "minecraft:black_concrete"
          },
          "g": {
            "tag": "forge:ingots/gold"
          }
        },
        "pattern": [
          "cgc",
          "gDg",
          "cIc"
        ],
        "result": {
          "item": "turtlechargingstation:turtle_charging_station"
        },
        "show_notification": true
      }
    }
  ]
}